setup.py
django_validate_on_save.egg-info/PKG-INFO
django_validate_on_save.egg-info/SOURCES.txt
django_validate_on_save.egg-info/dependency_links.txt
django_validate_on_save.egg-info/top_level.txt
validate_on_save/__init__.py
validate_on_save/apps.py
validate_on_save/models.py
validate_on_save/tests.py