Metadata-Version: 1.0
Name: django-validate-on-save
Version: 1.1.1
Summary: Automatically call full_clean() on models during save() to prevent invalid data being saved.
Home-page: http://github.com/brightinteractive/django-validate-on-save/
Author: Bright Interactive
Author-email: francis@bright-interactive.co.uk
License: BSD
Platform: UNKNOWN
